{"name":"渗透测试","slug":"渗透测试","count":2,"postlist":[{"title":"渗透测试之信息收集","uid":"4b515816a6e960006dfc09050d5893fe","slug":"渗透测试之信息搜集（持续更新）","date":"2023-01-10T13:21:22.739Z","updated":"2022-12-21T13:53:11.577Z","comments":true,"path":"api/articles/渗透测试之信息搜集（持续更新）.json","keywords":null,"cover":"https://abyssaler-typora-photobank.oss-cn-chengdu.aliyuncs.com/img_for_typorawallhaven-rr7xjq_1920x1080.png","text":"信息收集–渗透测试的灵魂信息收集需要收集哪些内容？为什么要收集这些？1.whois信息什么是whois？​ whois 指的是域名注册时留下的信息，比如留下管理员的名字、电话号码、邮箱 为什么要收集whois?​ 域名注册人可能就是网站管理员，可以尝试社工、套路，查询是不是注册了...","link":"","photos":[],"count_time":{"symbolsCount":"3.9k","symbolsTime":"4 mins."},"categories":[{"name":"学习笔记","slug":"学习笔记","count":13,"path":"api/categories/学习笔记.json"}],"tags":[{"name":"渗透测试","slug":"渗透测试","count":2,"path":"api/tags/渗透测试.json"}],"author":{"name":"Abyssaler","slug":"blog-author","avatar":"https://abyssaler-typora-photobank.oss-cn-chengdu.aliyuncs.com/img_for_typora/Face.jpg","link":"/","description":"道阻且长，行则将至","socials":{"github":"https://github.com/Abyssaler","twitter":"","stackoverflow":"","wechat":"","qq":"","weibo":"","zhihu":"","csdn":"https://blog.csdn.net/weixin_45349299","juejin":"","customs":{}}}},{"title":"渗透测试流程总结","uid":"8926bf7f2d1f8630ce6b123f3513e9c4","slug":"渗透测试流程","date":"2023-01-12T03:28:53.132Z","updated":"2023-01-12T02:39:48.044Z","comments":true,"path":"api/articles/渗透测试流程.json","keywords":null,"cover":"https://abyssaler-typora-photobank.oss-cn-chengdu.aliyuncs.com/img_for_typorawallhaven-8xg1zy.jpg","text":"渗透测试流程心得总结因为渗透测试过程非常复杂且涉及到的知识点极多，为了防止自己遗忘同时方便快速查阅，将渗透测试全流程以及其中涉及到的各种知识总结下来 1.确定目标确定你要渗透的目标，这里的前提是我们得经过用户的授权，才可以对网站进行渗透。不然如果我们没有经过客户的授权而对一个网站...","link":"","photos":[],"count_time":{"symbolsCount":"23k","symbolsTime":"21 mins."},"categories":[{"name":"学习笔记","slug":"学习笔记","count":13,"path":"api/categories/学习笔记.json"}],"tags":[{"name":"渗透测试","slug":"渗透测试","count":2,"path":"api/tags/渗透测试.json"}],"author":{"name":"Abyssaler","slug":"blog-author","avatar":"https://abyssaler-typora-photobank.oss-cn-chengdu.aliyuncs.com/img_for_typora/Face.jpg","link":"/","description":"道阻且长，行则将至","socials":{"github":"https://github.com/Abyssaler","twitter":"","stackoverflow":"","wechat":"","qq":"","weibo":"","zhihu":"","csdn":"https://blog.csdn.net/weixin_45349299","juejin":"","customs":{}}}}]}